setup.py
isi_sdk_9_1_0/__init__.py
isi_sdk_9_1_0/api_client.py
isi_sdk_9_1_0/configuration.py
isi_sdk_9_1_0/rest.py
isi_sdk_9_1_0.egg-info/PKG-INFO
isi_sdk_9_1_0.egg-info/SOURCES.txt
isi_sdk_9_1_0.egg-info/dependency_links.txt
isi_sdk_9_1_0.egg-info/requires.txt
isi_sdk_9_1_0.egg-info/top_level.txt
isi_sdk_9_1_0/api/__init__.py
isi_sdk_9_1_0/api/antivirus_api.py
isi_sdk_9_1_0/api/audit_api.py
isi_sdk_9_1_0/api/auth_api.py
isi_sdk_9_1_0/api/auth_groups_api.py
isi_sdk_9_1_0/api/auth_providers_api.py
isi_sdk_9_1_0/api/auth_roles_api.py
isi_sdk_9_1_0/api/auth_users_api.py
isi_sdk_9_1_0/api/avscan_api.py
isi_sdk_9_1_0/api/avscan_nodes_api.py
isi_sdk_9_1_0/api/certificate_api.py
isi_sdk_9_1_0/api/cloud_api.py
isi_sdk_9_1_0/api/cluster_api.py
isi_sdk_9_1_0/api/cluster_nodes_api.py
isi_sdk_9_1_0/api/debug_api.py
isi_sdk_9_1_0/api/dedupe_api.py
isi_sdk_9_1_0/api/event_api.py
isi_sdk_9_1_0/api/file_filter_api.py
isi_sdk_9_1_0/api/filepool_api.py
isi_sdk_9_1_0/api/filesystem_api.py
isi_sdk_9_1_0/api/fsa_api.py
isi_sdk_9_1_0/api/fsa_index_api.py
isi_sdk_9_1_0/api/fsa_results_api.py
isi_sdk_9_1_0/api/groupnets_summary_api.py
isi_sdk_9_1_0/api/hardening_api.py
isi_sdk_9_1_0/api/hardware_api.py
isi_sdk_9_1_0/api/healthcheck_api.py
isi_sdk_9_1_0/api/id_resolution_api.py
isi_sdk_9_1_0/api/id_resolution_zones_api.py
isi_sdk_9_1_0/api/ipmi_api.py
isi_sdk_9_1_0/api/job_api.py
isi_sdk_9_1_0/api/license_api.py
isi_sdk_9_1_0/api/local_api.py
isi_sdk_9_1_0/api/local_cluster_api.py
isi_sdk_9_1_0/api/namespace_api.py
isi_sdk_9_1_0/api/network_api.py
isi_sdk_9_1_0/api/network_groupnets_api.py
isi_sdk_9_1_0/api/network_groupnets_subnets_api.py
isi_sdk_9_1_0/api/performance_api.py
isi_sdk_9_1_0/api/performance_datasets_api.py
isi_sdk_9_1_0/api/protocols_api.py
isi_sdk_9_1_0/api/protocols_hdfs_api.py
isi_sdk_9_1_0/api/quota_api.py
isi_sdk_9_1_0/api/quota_quotas_api.py
isi_sdk_9_1_0/api/quota_reports_api.py
isi_sdk_9_1_0/api/snapshot_api.py
isi_sdk_9_1_0/api/snapshot_changelists_api.py
isi_sdk_9_1_0/api/snapshot_snapshots_api.py
isi_sdk_9_1_0/api/statistics_api.py
isi_sdk_9_1_0/api/storagepool_api.py
isi_sdk_9_1_0/api/storagepool_nodetypes_api.py
isi_sdk_9_1_0/api/sync_api.py
