Metadata-Version: 1.0
Name: isi-sdk-9-1-0
Version: 0.2.12
Summary: Isilon SDK
Home-page: UNKNOWN
Author: UNKNOWN
Author-email: sdk@isilon.com
License: UNKNOWN
Keywords: Swagger,Isilon SDK
Platform: UNKNOWN
